<?xml version="1.0" ?>
<review>
  <source value="http://www.buscape.com.br/avaliacao--pode-compar-vale-o-preco-que-paguei--samsung-dualview-tl210-12-0-megapixels--166348.html"/>
  <evaluation_date value="13/02/2011"/>
  <category value="Câmera Digital"/>
  <product value="Câmera Digital Samsung DualView TL210 12.0 Megapixels"/>
  <stars value="5.0"/>
  <recommends value="Yes"/>
  <user value="7303"/>
  <thumbsUp value="0"/>
  <thumbsDown value="0"/>
  <pros>Duração da Bateria
Custo-Benefício
Qualidade da Imagem
Facilidade de Uso
Portabilidade
Funções e Características
Memória Inclusa
Display
</pros>
  <cons>Não possui nenhum ponto negativo.
</cons>
  <opinion>a máquina é muito boa, facil de usar e de entender.

O que gostei: ela é muito boa

O que não gostei: ainda não achei nenhum</opinion>
</review>
