<?xml version="1.0" ?>
<review>
  <source value="http://www.buscape.com.br/avaliacao--lumix-16-1-excelente--panasonic-lumix-dmc-s5-16-1-megapixels--338346.html"/>
  <evaluation_date value="28/06/2012"/>
  <category value="Câmera Digital"/>
  <product value="Câmera Digital Panasonic Lumix DMC-S5 16.1 Megapixels"/>
  <stars value="5.0"/>
  <recommends value="Yes"/>
  <user value="15015"/>
  <thumbsUp value="0"/>
  <thumbsDown value="0"/>
  <pros>Duração da Bateria
Custo-Benefício
Qualidade da Imagem
Facilidade de Uso
Portabilidade
Funções e Características
Memória Inclusa
Display
</pros>
  <cons>Não possui nenhum ponto negativo.
</cons>
  <opinion>Esta câmera oferece ótima qualidade para fotos e videos, é fácil de configurar, por isso acho ela tão interessante, além de permitir fazer ajustes das fotos como retirar olhos vermelhos por exemplo, simplesmente ótima!

O que gostei: Fácil de usar, e otima qualidade.

O que não gostei: A tela poderia ser maior!</opinion>
</review>
