<?xml version="1.0" ?>
<review>
  <source value="http://www.buscape.com.br/avaliacao--otima-camera--sony-dsc-hx100v-16-2-megapixels--430560.html"/>
  <evaluation_date value="08/05/2013"/>
  <category value="Câmera Digital"/>
  <product value="Câmera Digital Sony DSC-HX100V 16.2 Megapixels"/>
  <stars value="5.0"/>
  <recommends value="Yes"/>
  <user value="12640"/>
  <thumbsUp value="0"/>
  <thumbsDown value="0"/>
  <pros>Custo-Benefício
Qualidade da Imagem
Facilidade de Uso
</pros>
  <cons>Duração da Bateria
</cons>
  <opinion>Não sou profissional, mas consultei alguns profissionais quando resolvi adquirir uma câmera de melhor qualidade que as portáteis comuns e esta foi a mais indicada. O produto atendeu as expectativas, tem fácil manuseio e funções interessantes (e que iniciantes, como eu, realmente conseguem usar!). A qualidade das fotos é ótima, o zoom de 30x é perfeito! A lente angular ajuda muito quando se fotografa objetos muito baixos ou muito altos. Também atendeu bem as minhas expectativas quanto a vídeos: ótima imagem, só deixa a desejar um pouco quanto ao som, que apresenta ruídos.</opinion>
</review>
