<?xml version="1.0" ?>
<review>
  <source value="http://www.buscape.com.br/avaliacao--um-sonho-de-produto--canon-eos-rebel-t3i-18-0-megapixels--455976.html"/>
  <evaluation_date value="11/07/2013"/>
  <category value="Câmera Digital"/>
  <product value="Câmera Digital Canon EOS Rebel T3i 18.0 Megapixels"/>
  <stars value="5.0"/>
  <recommends value="Yes"/>
  <user value="22234"/>
  <thumbsUp value="0"/>
  <thumbsDown value="0"/>
  <pros>Custo-Benefício
Qualidade da Imagem
Facilidade de Uso
Portabilidade
Funções e Características
Memória Inclusa
Display
</pros>
  <cons>Duração da Bateria
</cons>
  <opinion>ESSE PRODUTO SEM DÚVIDAS É MUITO BOM, MARCARAM OS MOMENTOS MAIS IMPORTANTES EM MINHA VIDA, SEM CONTAR QUE FIQUEI BEM NA FOTO. RSRS. EU RECOMENDO ESSE PRODUTO, POIS ELE É VERSÁTIL, LEVE E COMPACTO QUANDO COMPARADO A OUTRAS CÂMERAS DESSE MESMO NÍVEL, A QUALIDADE DA IMAGEM É PERFEITA, O FOCO É BEM AJUSTADO E POSSUI UM ZOOM INCRIVEL, SEM CONTAR QUE POSSUI UM DESIGNER MARAVILHOSO E PRA TODAS AS HORAS. UM DOS PONTOS NEGATIVOS QUE ENCONTREI, FOI A POUCA DURABILIDADE DA BATERIA. MAS, NO ENTANTO É UM EXELENTE PRODUTO, QUE RECOMENDO A TODOS PARA QUE POSSAM MARCAR OS MELHORES MOMENTOS DA VIDA ASSIM COMO MARQUEI OS MEUS.

</opinion>
</review>
