<?xml version="1.0" ?>
<review>
  <source value="http://www.buscape.com.br/avaliacao--melhor-nikon--nikon-slr-d90-12-3-megapixels--475865.html"/>
  <evaluation_date value="02/09/2013"/>
  <category value="Câmera Digital"/>
  <product value="Câmera Digital Nikon SLR D90 12.3 Megapixels"/>
  <stars value="5.0"/>
  <recommends value="Yes"/>
  <user value="20452"/>
  <thumbsUp value="0"/>
  <thumbsDown value="0"/>
  <pros>Duração da Bateria
Custo-Benefício
Qualidade da Imagem
Facilidade de Uso
Display
Granulação Mínima
</pros>
  <cons>Memória Inclusa
</cons>
  <opinion>Trabalho com Fotografia a quase 9 anos... Fotografo Casamentos, Aniversários, Bodas, enfim... Eventos em geral... A NIKON D90 foi uma câmera que me surpreendeu muito... Pelo custo, o resultado foi FANTÁSTICO. Uma Câmera leve, a cor das fotos ficam perfeitas, quando usado um ISO alto, a granulação é mínima, o que me encantou. Gostei dimais dessa câmera, comprei outra!</opinion>
</review>
