<?xml version="1.0" ?>
<review>
  <source value="http://www.buscape.com.br/avaliacao--adorooo--sony-cyber-shot-dsc-w630-16-1-megapixels--470263.html"/>
  <evaluation_date value="10/08/2013"/>
  <category value="Câmera Digital"/>
  <product value="Câmera Digital Sony Cyber-shot DSC-W630 16.1 Megapixels"/>
  <stars value="5.0"/>
  <recommends value="Yes"/>
  <user value="1551"/>
  <thumbsUp value="0"/>
  <thumbsDown value="0"/>
  <pros>Duração da Bateria
Qualidade da Imagem
Facilidade de Uso
Portabilidade
</pros>
  <cons>Memória Inclusa
</cons>
  <opinion>Essa camera é maravilhosa. Eu amo a minha e não vivo sem.</opinion>
</review>
