<?xml version="1.0" ?>
<review>
  <source value="http://www.buscape.com.br/avaliacao--nossa-que-maquina--olympus-x-775-7-1-megapixels--29588.html"/>
  <evaluation_date value="11/11/2008"/>
  <category value="Câmera Digital"/>
  <product value="Câmera Digital Olympus X-775 7.1 Megapixels"/>
  <stars value="5.0"/>
  <recommends value="Yes"/>
  <user value="18937"/>
  <thumbsUp value="1"/>
  <thumbsDown value="0"/>
  <pros>Duração da Bateria
Custo-Benefício
Qualidade da Imagem
Facilidade de Uso
Portabilidade
Funções e Características
Memória Inclusa
Display
</pros>
  <cons>Não possui nenhum ponto negativo.
</cons>
  <opinion>com esta resolução é tudo de bom podem acrditar

O que gostei: a resolução

O que não gostei: nenhuma</opinion>
</review>
