<?xml version="1.0" ?>
<review>
  <source value="http://www.buscape.com.br/avaliacao--otima-camera--agfaphoto-ap-selecta-16-0-megapixels--340973.html"/>
  <evaluation_date value="26/07/2012"/>
  <category value="Câmera Digital"/>
  <product value="Câmera Digital AgfaPhoto AP SELECTA 16.0 Megapixels"/>
  <stars value="5.0"/>
  <recommends value="Yes"/>
  <user value="12126"/>
  <thumbsUp value="1"/>
  <thumbsDown value="0"/>
  <pros>Duração da Bateria
Custo-Benefício
Qualidade da Imagem
Facilidade de Uso
Portabilidade
Funções e Características
Memória Inclusa
Display
</pros>
  <cons>Não possui nenhum ponto negativo.
</cons>
  <opinion>Produto perfeito, muito bom atendeu todas as minhas necessidades, fotos sairam perfeitas

O que gostei: Ela e otima para quem e iniciante, imagem perfeita

O que não gostei: Nenhum problema</opinion>
</review>
