<?xml version="1.0" ?>
<review>
  <source value="http://www.buscape.com.br/avaliacao--camera-sony-cyber-shot-dsc-h100--sony-cyber-shot-dsc-h100-16-1-megapixels--407954.html"/>
  <evaluation_date value="17/03/2013"/>
  <category value="Câmera Digital"/>
  <product value="Câmera Digital Sony Cyber-shot DSC-H100 16.1 Megapixels"/>
  <stars value="5.0"/>
  <recommends value="Yes"/>
  <user value="262"/>
  <thumbsUp value="5"/>
  <thumbsDown value="4"/>
  <pros>Custo-Benefício
Qualidade da Imagem
Facilidade de Uso
Portabilidade
Memória Inclusa
Display
</pros>
  <cons>Não possui nenhum ponto negativo.
</cons>
  <opinion>Qualidade, preço baixo e muito facil de usar é do tipo bbb, bom bonito e barato.</opinion>
</review>
