<?xml version="1.0" ?>
<review>
  <source value="http://www.buscape.com.br/avaliacao--superou-espectativas--samsung-wb850f-16-0-megapixels--403504.html"/>
  <evaluation_date value="10/03/2013"/>
  <category value="Câmera Digital"/>
  <product value="Câmera Digital Samsung WB850F 16.0 Megapixels"/>
  <stars value="5.0"/>
  <recommends value="Yes"/>
  <user value="24653"/>
  <thumbsUp value="1"/>
  <thumbsDown value="0"/>
  <pros>Custo-Benefício
Qualidade da Imagem
Facilidade de Uso
Portabilidade
Funções e Características
Display
</pros>
  <cons>a falta do thouch
</cons>
  <opinion>muito inovador , o melhor foi conectar com meu iphone e a parti dai foi so diverção minha namorada e minha mãe ja vão comprar uma cada otima cameras d+!!!</opinion>
</review>
