<?xml version="1.0" ?>
<review>
  <source value="http://www.buscape.com.br/avaliacao--camera-digital-sansung--samsung-dv150f-16-2-megapixels--473406.html"/>
  <evaluation_date value="22/08/2013"/>
  <category value="Câmera Digital"/>
  <product value="Câmera Digital Samsung DV150F 16.2 Megapixels"/>
  <stars value="5.0"/>
  <recommends value="Yes"/>
  <user value="28343"/>
  <thumbsUp value="2"/>
  <thumbsDown value="1"/>
  <pros>Duração da Bateria
Custo-Benefício
Qualidade da Imagem
Facilidade de Uso
Funções e Características
</pros>
  <cons>Não possui nenhum ponto negativo.
</cons>
  <opinion>Camera Digital Sansung, é um produto de ótima qualidade.
Tenho uma em modelo semelhante, porem já utilizei essa camera.
Sem duvida é ótima para fotos de frente ou normais, agora com essa febre de redes sociais a &quot;moda&quot; é tirar foto de todos os momentos.
Sem contar a qualidade da imagem, essas cameras são ótimas e duram muito, fazemos a troca geralmente por modelos mais atuais ou de uso profissional. Ótima para o uso do dia a dia.
Sem duvida um produto confiavel e com preço acessivel.</opinion>
</review>
