<?xml version="1.0" ?>
<review>
  <source value="http://www.buscape.com.br/avaliacao--produto-fantastico--sony-cyber-shot-dsc-w200-12-1-megapixels--22135.html"/>
  <evaluation_date value="26/02/2008"/>
  <category value="Câmera Digital"/>
  <product value="Câmera Digital Sony Cyber-shot DSC-W200 12.1 Megapixels"/>
  <stars value="5.0"/>
  <recommends value="Yes"/>
  <user value="23993"/>
  <thumbsUp value="5"/>
  <thumbsDown value="3"/>
  <pros>Duração da Bateria
Custo-Benefício
Qualidade da Imagem
Facilidade de Uso
Portabilidade
Funções e Características
Memória Inclusa
Display
</pros>
  <cons>Não possui nenhum ponto negativo.
</cons>
  <opinion>Maquina com recursos profissionais, somente encontrados em camaras do genero, excelente custo beneficio. A qualidade das fotos são indiscutiveis.

O que gostei: Maquina digital para uso profissional

O que não gostei: não há nada que possa dizer de contra</opinion>
</review>
