<?xml version="1.0" ?>
<review>
  <source value="http://www.buscape.com.br/avaliacao--qualidade-de-imagem-e-custo-benificio-ruins--fujifilm-finepix-s4500-14-0-megapixels--480280.html"/>
  <evaluation_date value="21/09/2013"/>
  <category value="Câmera Digital"/>
  <product value="Câmera Digital Fujifilm FinePix S4500 14.0 Megapixels"/>
  <stars value="2.0"/>
  <recommends value=""/>
  <user value="20761"/>
  <thumbsUp value="0"/>
  <thumbsDown value="0"/>
  <pros>Não possui nenhum ponto positivo.
</pros>
  <cons>Custo-Benefício
Qualidade da Imagem
Memória Inclusa
</cons>
  <opinion>Comprei essa câmera há alguns meses atrás principalmente por causa do preço muito inferior a maioria das câmeras da mesma categoria existentes no mercado. Me arrependi muito porque a qualidade das fotos, e a não existência de uma memória interna e a bateria (que é de quatro pilhas normais) faz com que o produto seja muito ruim.
A única coisa que realmente vale a pena é zoom óptico de 30x.
O principal defeito é a qualidade da imagem, a Fuji S4500 é uma câmera semiprofissional, mas tira fotos com qualidade inferior às do meu celular Samsung Galaxy One. É algo inacreditável.
Se você deseja comprar uma câmera semiprofissional, gaste alguns reais a mais e compre de uma marca reconhecida como Nikon e Cannon, você com certeza não terá o arrependimento que eu tive.</opinion>
</review>
