<?xml version="1.0" ?>
<review>
  <source value="http://www.buscape.com.br/avaliacao--avaliacao-nikon-l810--nikon-coolpix-l810-16-1-megapixels--392384.html"/>
  <evaluation_date value="14/12/2012"/>
  <category value="Câmera Digital"/>
  <product value="Câmera Digital Nikon Coolpix L810 16.1 Megapixels"/>
  <stars value="2.0"/>
  <recommends value=""/>
  <user value="7303"/>
  <thumbsUp value="5"/>
  <thumbsDown value="2"/>
  <pros>Qualidade da Imagem
Portabilidade
Memória Inclusa
</pros>
  <cons>Duração da Bateria
Custo-Benefício
Facilidade de Uso
Funções e Características
Display
</cons>
  <opinion>Pelo preço pago ficaria satisfeita com outra máquina fotográfica. Primeira vez que adquiro um produto da Nikon e não gostei.

O que gostei: modelo bonito e impressiona.

O que não gostei: Não gostei do sistema de pilhas, o manuseio do zoom não é prático, o lay out  não é fácil de usar e de ajustar os comandos na hora de fotografar.</opinion>
</review>
