<?xml version="1.0" ?>
<review>
  <source value="http://www.buscape.com.br/avaliacao--tudo-de-bom-recomendo--samsung-es60-12-2-megapixels--63585.html"/>
  <evaluation_date value="12/12/2009"/>
  <category value="Câmera Digital"/>
  <product value="Câmera Digital Samsung ES60 12.2 Megapixels"/>
  <stars value="0.0"/>
  <recommends value="Yes"/>
  <user value="4437"/>
  <thumbsUp value="12"/>
  <thumbsDown value="1"/>
  <pros>Não possui nenhum ponto positivo.
</pros>
  <cons>Duração da Bateria
Custo-Benefício
Qualidade da Imagem
Facilidade de Uso
Portabilidade
Funções e Características
Memória Inclusa
Display
</cons>
  <opinion>Meu essa é a melhor camera digital que ja vi..

O que gostei: Melhor qualidade de imagem

O que não gostei: Nenhum</opinion>
</review>
