<?xml version="1.0" ?>
<review>
  <source value="http://www.buscape.com.br/avaliacao--otima-camera--sony-cyber-shot-dsc-w290-12-1-megapixels--67654.html"/>
  <evaluation_date value="18/01/2010"/>
  <category value="Câmera Digital"/>
  <product value="Câmera Digital Sony Cyber-shot DSC-W290 12.1 Megapixels"/>
  <stars value="0.0"/>
  <recommends value=""/>
  <user value="26895"/>
  <thumbsUp value="3"/>
  <thumbsDown value="0"/>
  <pros>Não possui nenhum ponto positivo.
</pros>
  <cons>Duração da Bateria
Custo-Benefício
Qualidade da Imagem
Facilidade de Uso
Portabilidade
Funções e Características
Memória Inclusa
Display
</cons>
  <opinion>òtimo produto, excelente qualidade de resolução nas fotos e nos vídeos de alta definição. Estou satisfeito!

O que gostei: òtimo produto, excelente qualidade de resolução nas fotos e nos vídeos de alta definição. Estou satisfeito!

O que não gostei: Não tem menu em portugues, o que na verdade pra mim não tem problema algum, coloquei em espanhol e da pra entender muito bem.</opinion>
</review>
