<?xml version="1.0" ?>
<review>
  <source value="http://www.buscape.com.br/avaliacao--pode-comprar-pois-eu-acho-q-deve-ser-muito-boa--vivitar-vivicam-5024-5-1-megapixels--132017.html"/>
  <evaluation_date value="20/10/2010"/>
  <category value="Câmera Digital"/>
  <product value="Câmera Digital Vivitar ViviCam 5024 5.1 Megapixels"/>
  <stars value="0.0"/>
  <recommends value="Yes"/>
  <user value="28448"/>
  <thumbsUp value="0"/>
  <thumbsDown value="1"/>
  <pros>Não possui nenhum ponto positivo.
</pros>
  <cons>Duração da Bateria
Custo-Benefício
Qualidade da Imagem
Facilidade de Uso
Portabilidade
Funções e Características
Memória Inclusa
Display
</cons>
  <opinion>não sei como é esta camera mais eu comcerteza compraria ela

O que gostei: sim

O que não gostei: nao</opinion>
</review>
