<?xml version="1.0" ?>
<review>
  <source value="http://www.buscape.com.br/avaliacao--quero-saber-quanto-que-custa-a-camera-sony-dsc-p32--sony-cyber-shot-dsc-p32-3-2-megapixels--34828.html"/>
  <evaluation_date value="25/01/2009"/>
  <category value="Câmera Digital"/>
  <product value="Câmera Digital Sony Cyber-shot DSC-P32 3.2 Megapixels"/>
  <stars value="1.0"/>
  <recommends value=""/>
  <user value="7868"/>
  <thumbsUp value="3"/>
  <thumbsDown value="0"/>
  <pros>Qualidade da Imagem
Facilidade de Uso
</pros>
  <cons>Duração da Bateria
Custo-Benefício
Portabilidade
Funções e Características
Memória Inclusa
Display
</cons>
  <opinion>e uma otima maquina,pena k as pilhas nao dura muito tempo.

O que gostei: as fotos

O que não gostei: a bateria e muito fraca</opinion>
</review>
