<?xml version="1.0" ?>
<review>
  <source value="http://www.buscape.com.br/avaliacao--custo-beneficio---agfaphoto-compact-102-12-0-megapixels--197358.html"/>
  <evaluation_date value="12/05/2011"/>
  <category value="Câmera Digital"/>
  <product value="Câmera Digital AgfaPhoto Compact 102 12.0 Megapixels"/>
  <stars value="3.0"/>
  <recommends value="Yes"/>
  <user value="7303"/>
  <thumbsUp value="0"/>
  <thumbsDown value="0"/>
  <pros>Custo-Benefício
Qualidade da Imagem
Facilidade de Uso
Portabilidade
Funções e Características
Display
</pros>
  <cons>Duração da Bateria
Memória Inclusa
</cons>
  <opinion>um protuto muito bom, custo-beneficio foi o que mais me atraiu.

O que gostei: qualidade de imagem muito boa.

O que não gostei: usa pilhas, deveria ser bateria</opinion>
</review>
