<?xml version="1.0" ?>
<review>
  <source value="http://www.buscape.com.br/avaliacao--compras-via-internet--ge-smart-j1455-14-1-megapixels--241005.html"/>
  <evaluation_date value="06/09/2011"/>
  <category value="Câmera Digital"/>
  <product value="Câmera Digital GE Smart J1455 14.1 Megapixels"/>
  <stars value="3.0"/>
  <recommends value="Yes"/>
  <user value="7303"/>
  <thumbsUp value="0"/>
  <thumbsDown value="0"/>
  <pros>Custo-Benefício
Facilidade de Uso
Portabilidade
Funções e Características
Memória Inclusa
</pros>
  <cons>Duração da Bateria
Qualidade da Imagem
Display
</cons>
  <opinion>Estava precisando de uma câmera, pois a minha havia quebrado, e naquele momento não podia gastar muito com a aquisição do produto, pesquisei, comparei preços e foi a que melhor se encaixou no meu orçamento. Gosto do produto.

O que gostei: É compacta e o preço é bom.

O que não gostei: A bateria não dura.</opinion>
</review>
