<?xml version="1.0" ?>
<review>
  <source value="http://www.buscape.com.br/avaliacao-positiva-sobre--mitsuca-ds6083br-6-0-megapixels.html"/>
  <evaluation_date value="02/02/2010"/>
  <category value="Câmera Digital"/>
  <product value="Câmera Digital Mitsuca DS6083BR 6.0 Megapixels"/>
  <stars value="3.0"/>
  <recommends value="Yes"/>
  <user value="7303"/>
  <thumbsUp value="0"/>
  <thumbsDown value="0"/>
  <pros>Custo-Benefício
Facilidade de Uso
Portabilidade
Memória Inclusa
Display
</pros>
  <cons>Duração da Bateria
Qualidade da Imagem
Funções e Características
</cons>
  <opinion>OS PRODUTOS QUE ADQUIRI NA VIA BLU NÃO TEM NADA A VER COM O PRODUTO QUE ESTÃO SOLICITANDO OPINIÃO.

O que gostei: O TAMANHO E FACILIDADE DE UTILIZAR O APARELHO.

O que não gostei: AS FOTOS TIRADAS À NOITE NÃO FICAM BOAS.
</opinion>
</review>
