<?xml version="1.0" ?>
<review>
  <source value="http://www.buscape.com.br/avaliacao--o-produto-ate-o-momento-eh-de-boa-quac--sony-cyber-shot-dsc-w530-14-1-megapixels--246462.html"/>
  <evaluation_date value="19/09/2011"/>
  <category value="Câmera Digital"/>
  <product value="Câmera Digital Sony Cyber-shot DSC-W530 14.1 Megapixels"/>
  <stars value="3.0"/>
  <recommends value="Yes"/>
  <user value="7303"/>
  <thumbsUp value="6"/>
  <thumbsDown value="1"/>
  <pros>Duração da Bateria
Qualidade da Imagem
Portabilidade
Funções e Características
Memória Inclusa
Display
</pros>
  <cons>Custo-Benefício
Facilidade de Uso
</cons>
  <opinion>o produto eh compacto e de facil manuseio

O que gostei: as fotos possuem boa nitidez e bom contraste de cores

O que não gostei: poderia ter a lingua portuguesa no menu</opinion>
</review>
