<?xml version="1.0" ?>
<review>
  <source value="http://www.buscape.com.br/avaliacao--recomendo--smartphone-nokia-n95-desbloqueado--21616.html"/>
  <evaluation_date value="31/12/2007"/>
  <category value="Celular e Smartphone"/>
  <product value="Celular e Smartphone Smartphone Nokia N95 Desbloqueado"/>
  <stars value="4.0"/>
  <recommends value="Yes"/>
  <user value="26798"/>
  <thumbsUp value="61"/>
  <thumbsDown value="12"/>
  <pros>Duração da Bateria
Design
Custo-Benefício
</pros>
  <cons>Não possui nenhum ponto negativo.
</cons>
  <opinion>O aparelho reune GPS, câmera fotográfica de 5mp, agenda, smartfone (acesso a Internet, aplicativos word, excel e power point e celular num único aparelho.

O que gostei: Smartfone leve, teclado reduzido e GPS. Pode baixar os contatos pelo outlook e gerenciar agenda.

O que não gostei: Não encontrei capa para ele. Somente versão prata.</opinion>
</review>
