<?xml version="1.0" ?>
<review>
  <source value="http://www.buscape.com.br/avaliacao--alcatel-ot-710--celular-alcatel-ot-710-desbloqueado--243802.html"/>
  <evaluation_date value="12/09/2011"/>
  <category value="Celular e Smartphone"/>
  <product value="Celular e Smartphone Celular Alcatel OT-710 Desbloqueado"/>
  <stars value="4.0"/>
  <recommends value="Yes"/>
  <user value="24064"/>
  <thumbsUp value="4"/>
  <thumbsDown value="0"/>
  <pros>Duração da Bateria
Design
Custo-Benefício
Facilidade de Uso
Funções e Características
Durabilidade
Display
Operadora
Câmera
</pros>
  <cons>Não possui nenhum ponto negativo.
</cons>
  <opinion>Trata-se de um aparelho muito bom e de bom preço

O que gostei: Design e custo/beneficio.o aparelho tem muito recursos. Bonito , tamanho muito bom, se escuta muito bem.

O que não gostei: O manual não ensina quase nada, daí inicialmente vc acha ruim o aparelho,</opinion>
</review>
