<?xml version="1.0" ?>
<review>
  <source value="http://www.buscape.com.br/avaliacao--otimo--celular-nokia-c3-desbloqueado--132836.html"/>
  <evaluation_date value="26/10/2010"/>
  <category value="Celular e Smartphone"/>
  <product value="Celular e Smartphone Celular Nokia C3 Desbloqueado"/>
  <stars value="4.0"/>
  <recommends value="Yes"/>
  <user value="13508"/>
  <thumbsUp value="15"/>
  <thumbsDown value="8"/>
  <pros>Duração da Bateria
Design
Custo-Benefício
Facilidade de Uso
Funções e Características
Durabilidade
Display
Operadora
</pros>
  <cons>Câmera
</cons>
  <opinion>Por mais que não tenha conectividade 3G, o acesso a internet é rápido e sem complicações.
A organização das conversas por SMS é muito prático.
É um produto muito funcional, perfeito pra quem vive conectado a redes sociais !!!!

O que gostei: design, internet, modelo das mensagens, facilidade de digitação... PREÇO !!!

O que não gostei: NADA A DECLARAR POR ENQUANTO</opinion>
</review>
