<?xml version="1.0" ?>
<review>
  <source value="http://www.buscape.com.br/avaliacao--excelente-aparelho---smartphone-lg-optimus-3d-p920-desbloqueado--319586.html"/>
  <evaluation_date value="03/04/2012"/>
  <category value="Celular e Smartphone"/>
  <product value="Celular e Smartphone Smartphone LG Optimus 3D P920 Desbloqueado"/>
  <stars value="4.0"/>
  <recommends value="Yes"/>
  <user value="7303"/>
  <thumbsUp value="0"/>
  <thumbsDown value="1"/>
  <pros>Design
Custo-Benefício
Facilidade de Uso
Funções e Características
Durabilidade
Display
Operadora
Câmera
</pros>
  <cons>Duração da Bateria
</cons>
  <opinion>Nada igual. O 3D é um show.

O que gostei: Tela muito boa. O 3D impressiona.

O que não gostei: Não tem muitos acessórios específicos.</opinion>
</review>
