<?xml version="1.0" ?>
<review>
  <source value="http://www.buscape.com.br/avaliacao--dont--smartphone-motorola-defy-mb525-desbloqueado--235888.html"/>
  <evaluation_date value="22/08/2011"/>
  <category value="Celular e Smartphone"/>
  <product value="Celular e Smartphone Smartphone Motorola Defy MB525 Desbloqueado"/>
  <stars value="4.0"/>
  <recommends value="Yes"/>
  <user value="11546"/>
  <thumbsUp value="0"/>
  <thumbsDown value="2"/>
  <pros>Design
Custo-Benefício
Facilidade de Uso
Funções e Características
Durabilidade
Display
Operadora
Câmera
</pros>
  <cons>Duração da Bateria
</cons>
  <opinion>ele é muito bom legal util muito pequeno fino uma beleza


O que gostei: ele é muito bom e util

O que não gostei: hi don´t fuckiu ever never say no to racins and but I´m don´t ever it bod</opinion>
</review>
