<?xml version="1.0" ?>
<review>
  <source value="http://www.buscape.com.br/avaliacao--otima-qualidade---smartphone-sony-ericsson-xperia-x10-mini-desbloqueado--416131.html"/>
  <evaluation_date value="27/03/2013"/>
  <category value="Celular e Smartphone"/>
  <product value="Celular e Smartphone Smartphone Sony Ericsson Xperia X10 mini Desbloqueado"/>
  <stars value="5.0"/>
  <recommends value="Yes"/>
  <user value="20416"/>
  <thumbsUp value="0"/>
  <thumbsDown value="0"/>
  <pros>Design
Facilidade de Uso
Câmera
</pros>
  <cons>Duração da Bateria
</cons>
  <opinion>Design lindo, facilidade de uso e valor de custo acessivel .</opinion>
</review>
