<?xml version="1.0" ?>
<review>
  <source value="http://www.buscape.com.br/avaliacao--melhor-smartphone-android-por-menos-de-r2000--smartphone-lg-nexus-4-e960-desbloqueado--445430.html"/>
  <evaluation_date value="17/06/2013"/>
  <category value="Celular e Smartphone"/>
  <product value="Celular e Smartphone Smartphone LG Nexus 4 E960 Desbloqueado"/>
  <stars value="5.0"/>
  <recommends value="Yes"/>
  <user value="1350"/>
  <thumbsUp value="0"/>
  <thumbsDown value="0"/>
  <pros>Duração da Bateria
Custo-Benefício
Facilidade de Uso
Funções e Características
Display
Câmera
</pros>
  <cons>Cartão Memoria
</cons>
  <opinion>Esse aparelho é o melhor custo beneficio do mercado hoje, é melhor aparelho android por menos de 2 mil, tela com resolução 720p, câmera com 8mp, 16gb de armazenamento (12GB acessível para o usuário e como ponto negativo é não ter um slot para cartão SD),   o som do aparelho é bom, a bateria dura o dia todo (sem uso abusivo, com sync de amil e redes sociais, jogos simples, mp3 e um pouco de navegação web). Tenho um a 1 mês e acho que meu investimento foi muito bom.</opinion>
</review>
