<?xml version="1.0" ?>
<review>
  <source value="http://www.buscape.com.br/avaliacao--o-melhor-smartfone-do-m-u-n-d-o-d--smartphone-apple-iphone-4s-32gb-desbloqueado--452205.html"/>
  <evaluation_date value="04/07/2013"/>
  <category value="Celular e Smartphone"/>
  <product value="Celular e Smartphone Smartphone Apple iPhone 4S 32GB Desbloqueado"/>
  <stars value="5.0"/>
  <recommends value="Yes"/>
  <user value="22969"/>
  <thumbsUp value="0"/>
  <thumbsDown value="0"/>
  <pros>Duração da Bateria
Design
Custo-Benefício
Facilidade de Uso
Funções e Características
Durabilidade
Display
Câmera
melhor do mundo
</pros>
  <cons>Nenhum
</cons>
  <opinion>OMG... Este é um aparelho de comunicação que muitos querem ter um dia! iPHONE sem dúvida é o melhor telefone móvel que vem conquistando o MUNDO. Sua tela de 4 polegadas é ótima para comentar,tuitar,jogar,escrever mensagens e e-mails.A câmera certamente é incrível com 8 megapixels que transmitirá na galeria muitas emoções gravadas facilmente na filmadora HD.
O novo iOS 6 é muito fácil para aprender e desfrutar do melhor no aparelho.
Eu realmente quero ter um iPhone 5 e recomendo muiiitttooo,pois ele é simplesmente PERFEITO!!!!</opinion>
</review>
