<?xml version="1.0" ?>
<review>
  <source value="http://www.buscape.com.br/avaliacao--perfeito--smartphone-blackberry-z10-desbloqueado--466340.html"/>
  <evaluation_date value="29/07/2013"/>
  <category value="Celular e Smartphone"/>
  <product value="Celular e Smartphone Smartphone BlackBerry Z10 Desbloqueado"/>
  <stars value="5.0"/>
  <recommends value="Yes"/>
  <user value="26464"/>
  <thumbsUp value="0"/>
  <thumbsDown value="0"/>
  <pros>Duração da Bateria
Design
Facilidade de Uso
Funções e Características
Durabilidade
Display
Câmera
</pros>
  <cons>Custo-Benefício
</cons>
  <opinion>O designe é perfeito assim como o tamanho da tela, facilidade de uso, câmera de alta definição. Enfim, um conjunto perfeito.</opinion>
</review>
