<?xml version="1.0" ?>
<review>
  <source value="http://www.buscape.com.br/avaliacao--lg-l5-o-smartphone-q-ira-te-surpreender-por-experiencia-propria---smartphone-lg-optimus-l5-ii-dual-e455-desbloqueado--461598.html"/>
  <evaluation_date value="22/07/2013"/>
  <category value="Celular e Smartphone"/>
  <product value="Celular e Smartphone Smartphone LG Optimus L5 II Dual E455 Desbloqueado"/>
  <stars value="5.0"/>
  <recommends value="Yes"/>
  <user value="16992"/>
  <thumbsUp value="0"/>
  <thumbsDown value="0"/>
  <pros>Duração da Bateria
Design
Custo-Benefício
Facilidade de Uso
Funções e Características
Durabilidade
Display
Câmera
além disso tudo tem senso
r de voz
</pros>
  <cons>Não possui nenhum ponto negativo.
</cons>
  <opinion>Depois da minha compra a 10 meses, pelo q eu fiz com ele eu gostei muito do produto, muito bom.
Ele é um smartphone muito bom dual chip, o mais legal é o sensor de voz na configuração, na net e na câmera.
a internet é muito boa com wifi e 3g. o seu processador é muito bom não trava nem nada e etc. seu desing muito lindo e fino eu recomendo a todos muito bom.</opinion>
</review>
