<?xml version="1.0" ?>
<review>
  <source value="http://www.buscape.com.br/avaliacao--so-coisas-boas---smartphone-apple-iphone-4-8gb-desbloqueado--477955.html"/>
  <evaluation_date value="10/09/2013"/>
  <category value="Celular e Smartphone"/>
  <product value="Celular e Smartphone Smartphone Apple iPhone 4 8GB Desbloqueado"/>
  <stars value="5.0"/>
  <recommends value="Yes"/>
  <user value="20256"/>
  <thumbsUp value="0"/>
  <thumbsDown value="0"/>
  <pros>Design
Custo-Benefício
Facilidade de Uso
Funções e Características
Display
Câmera
</pros>
  <cons>nemhum
</cons>
  <opinion>Não tenho nem uma experiência mais sou louca para comprar esse aparelho celular.</opinion>
</review>
