<?xml version="1.0" ?>
<review>
  <source value="http://www.buscape.com.br/avaliacao--otimo-produto--smartphone-sony-ericsson-xperia-play-desbloqueado--475450.html"/>
  <evaluation_date value="31/08/2013"/>
  <category value="Celular e Smartphone"/>
  <product value="Celular e Smartphone Smartphone Sony Ericsson Xperia PLAY Desbloqueado"/>
  <stars value="5.0"/>
  <recommends value="Yes"/>
  <user value="24521"/>
  <thumbsUp value="0"/>
  <thumbsDown value="0"/>
  <pros>Duração da Bateria
Design
Custo-Benefício
Facilidade de Uso
Durabilidade
Display
</pros>
  <cons>Funções e Características
Câmera
</cons>
  <opinion>otimo produto e bem versátil, bom para passar o tempo e quase um PSP.</opinion>
</review>
