<?xml version="1.0" ?>
<review>
  <source value="http://www.buscape.com.br/avaliacao--celular--celular-motorola-w180-desbloqueado--50346.html"/>
  <evaluation_date value="06/08/2009"/>
  <category value="Celular e Smartphone"/>
  <product value="Celular e Smartphone Celular Motorola W180 Desbloqueado"/>
  <stars value="5.0"/>
  <recommends value="Yes"/>
  <user value="6921"/>
  <thumbsUp value="0"/>
  <thumbsDown value="0"/>
  <pros>Duração da Bateria
Design
Custo-Benefício
Facilidade de Uso
Funções e Características
Durabilidade
Display
Operadora
</pros>
  <cons>Não possui nenhum ponto negativo.
</cons>
  <opinion>Excelente celular e vem desbloqueado.Otimo preço e boa qualidade

O que gostei: Leve, prático de usar e ainda vem com rádio.

O que não gostei: Sem reclamações.</opinion>
</review>
