<?xml version="1.0" ?>
<review>
  <source value="http://www.buscape.com.br/avaliacao--um-celular-que-compensa-a-compra--celular-lg-kf245-desbloqueado--26416.html"/>
  <evaluation_date value="08/10/2008"/>
  <category value="Celular e Smartphone"/>
  <product value="Celular e Smartphone Celular LG KF245 Desbloqueado"/>
  <stars value="5.0"/>
  <recommends value="Yes"/>
  <user value="2792"/>
  <thumbsUp value="16"/>
  <thumbsDown value="6"/>
  <pros>Duração da Bateria
Design
Custo-Benefício
Facilidade de Uso
Funções e Características
Durabilidade
Display
Operadora
</pros>
  <cons>Não possui nenhum ponto negativo.
</cons>
  <opinion>O celular é de ultima geração e tem o preço de celular bem baratinho.

O que gostei: Um celular multimídia com uma camera de 2 mega-piexel.
Um design elegante e clean.

O que não gostei: Nada contra é perfeito!</opinion>
</review>
