<?xml version="1.0" ?>
<review>
  <source value="http://www.buscape.com.br/avaliacao--muito-bom--smartphone-nokia-lumia-920-com-windows-phone--455909.html"/>
  <evaluation_date value="11/07/2013"/>
  <category value="Celular e Smartphone"/>
  <product value="Celular e Smartphone Smartphone Nokia Lumia 920 com Windows Phone"/>
  <stars value="5.0"/>
  <recommends value="Yes"/>
  <user value="10694"/>
  <thumbsUp value="1"/>
  <thumbsDown value="0"/>
  <pros>Design
Custo-Benefício
Facilidade de Uso
Funções e Características
Durabilidade
Display
Câmera
falta de apps
</pros>
  <cons>Duração da Bateria
</cons>
  <opinion>Eu tenho experiência com o Lumia 800, o sistema operacional é de muito fácil utilização, o único problema é a falta de alguns apps bem comuns a outros celulares, assim como Instagram por exemplo, facebook messenger, youtube, jogos fracos entre outros.</opinion>
</review>
