<?xml version="1.0" ?>
<review>
  <source value="http://www.buscape.com.br/avaliacao--mais-q-d---celular-motorola-razr2-v9-desbloqueado--35282.html"/>
  <evaluation_date value="03/02/2009"/>
  <category value="Celular e Smartphone"/>
  <product value="Celular e Smartphone Celular Motorola Razr2 V9 Desbloqueado"/>
  <stars value="5.0"/>
  <recommends value="Yes"/>
  <user value="11530"/>
  <thumbsUp value="2"/>
  <thumbsDown value="0"/>
  <pros>Duração da Bateria
Design
Custo-Benefício
Facilidade de Uso
Funções e Características
Durabilidade
Display
Operadora
</pros>
  <cons>Não possui nenhum ponto negativo.
</cons>
  <opinion>recomendo para todos maravilhoso celular adorei bom mesmo


O que gostei: bom facil de usar e muito barato</opinion>
</review>
