<?xml version="1.0" ?>
<review>
  <source value="http://www.buscape.com.br/avaliacao--muito-bom--smartphone-lg-optimus-g-e977-desbloqueado--438661.html"/>
  <evaluation_date value="28/05/2013"/>
  <category value="Celular e Smartphone"/>
  <product value="Celular e Smartphone Smartphone LG Optimus G E977 Desbloqueado"/>
  <stars value="5.0"/>
  <recommends value="Yes"/>
  <user value="25547"/>
  <thumbsUp value="2"/>
  <thumbsDown value="0"/>
  <pros>Duração da Bateria
Custo-Benefício
Facilidade de Uso
Funções e Características
Durabilidade
Display
Câmera
</pros>
  <cons>Design
</cons>
  <opinion>Muito bom! fácil de usar!
gosti bastante e estou muito satisfeita, sempre tive problemas com celular, sou exigente para celular, mas este me atendeu perfeitamente e superou minhas expectativas</opinion>
</review>
