<?xml version="1.0" ?>
<review>
  <source value="http://www.buscape.com.br/avaliacao--celular-samsung-beam--smartphone-samsung-galaxy-beam-gt-i8530-desbloqueado--394347.html"/>
  <evaluation_date value="19/12/2012"/>
  <category value="Celular e Smartphone"/>
  <product value="Celular e Smartphone Smartphone Samsung Galaxy Beam GT-I8530 Desbloqueado"/>
  <stars value="5.0"/>
  <recommends value="Yes"/>
  <user value="14067"/>
  <thumbsUp value="0"/>
  <thumbsDown value="2"/>
  <pros>Duração da Bateria
Design
Custo-Benefício
Facilidade de Uso
Funções e Características
Durabilidade
Display
Operadora
Câmera
</pros>
  <cons>Não possui nenhum ponto negativo.
</cons>
  <opinion>esse aparelho celular é muito bom, principalmente porque podemos compartilhar fotos e videos em qualquer lugar com nossos amigos - como se estivesse-mos em um cinema

O que gostei: funcionalidade do retroporjetor

O que não gostei: NAO TENHO NADA CONTRA O PRODUTOS - NA MINHA OPINIAO ELE É OTIMO</opinion>
</review>
