<?xml version="1.0" ?>
<review>
  <source value="http://www.buscape.com.br/avaliacao--otima-compra--olympus-fe-5030-14-megapixels--238282.html"/>
  <evaluation_date value="29/08/2011"/>
  <category value="Câmera Digital"/>
  <product value="Câmera Digital Olympus FE-5030 14 Megapixels"/>
  <stars value="4.0"/>
  <recommends value=""/>
  <user value="15172"/>
  <thumbsUp value="0"/>
  <thumbsDown value="0"/>
  <pros>Custo-Benefício
Facilidade de Uso
Portabilidade
Funções e Características
Memória Inclusa
Display
</pros>
  <cons>Duração da Bateria
Qualidade da Imagem
</cons>
  <opinion>ótimo custo beneficio.a camera é boa,edtou satisfeito.

O que gostei: otimo zoom,desine muito bonito e bateria boa.

O que não gostei: a imagem poderia ser melhor,é mais ou menos.</opinion>
</review>
