<?xml version="1.0" ?>
<review>
  <source value="http://www.buscape.com.br/avaliacao--8723-d-spala--sony-cyber-shot-dsc-w630-16-1-megapixels--352693.html"/>
  <evaluation_date value="06/09/2012"/>
  <category value="Câmera Digital"/>
  <product value="Câmera Digital Sony Cyber-shot DSC-W630 16.1 Megapixels"/>
  <stars value="4.0"/>
  <recommends value="Yes"/>
  <user value="8723"/>
  <thumbsUp value="0"/>
  <thumbsDown value="0"/>
  <pros>Duração da Bateria
Custo-Benefício
Qualidade da Imagem
Facilidade de Uso
Portabilidade
Funções e Características
Memória Inclusa
Display
</pros>
  <cons>Não possui nenhum ponto negativo.
</cons>
  <opinion>Gostei da camera, muito boa com super facilidade para lidar com a mesma, tudo em seu menu e bem explicado, nota 10

O que gostei:  portabilidade, leveza, pequena, tudo de bom, fotos maravilhosas.

O que não gostei:  não vem com porta camera acho um erro das empresas fabricantes...</opinion>
</review>
