<?xml version="1.0" ?>
<review>
  <source value="http://www.buscape.com.br/avaliacao--recomendo--fujifilm-finepix-s4000-14-0-megapixels--363102.html"/>
  <evaluation_date value="02/10/2012"/>
  <category value="Câmera Digital"/>
  <product value="Câmera Digital Fujifilm FinePix S4000 14.0 Megapixels"/>
  <stars value="4.0"/>
  <recommends value="Yes"/>
  <user value="26902"/>
  <thumbsUp value="0"/>
  <thumbsDown value="0"/>
  <pros>Custo-Benefício
Qualidade da Imagem
Facilidade de Uso
Portabilidade
Funções e Características
Memória Inclusa
Display
</pros>
  <cons>Duração da Bateria
</cons>
  <opinion>Gostei muito dessa câmera semi-profissional pois lhe dá mais recursos do que aquelas de bolso.  Precisei tirar uma foto com o zoom e fiquei surpresa com a nitidez da imagem.  Geralmente os zooms ópticos me deixavam bastante decepcionadas.

O que gostei: òtimo zoom e igualmente a qualidade das fotos. Leve e fácil de manejar

O que não gostei: É preciso estudar o manual para conhecer melhor todos os recursos que possui.  É meio complicado.</opinion>
</review>
