<?xml version="1.0" ?>
<review>
  <source value="http://www.buscape.com.br/avaliacao--gostei-da-maquina---samsung-es90-14-2-megapixels--393513.html"/>
  <evaluation_date value="08/01/2013"/>
  <category value="Câmera Digital"/>
  <product value="Câmera Digital Samsung ES90 14.2 Megapixels"/>
  <stars value="4.0"/>
  <recommends value="Yes"/>
  <user value="7303"/>
  <thumbsUp value="0"/>
  <thumbsDown value="0"/>
  <pros>Custo-Benefício
Qualidade da Imagem
Facilidade de Uso
Portabilidade
Funções e Características
Display
</pros>
  <cons>Duração da Bateria
Memória Inclusa
</cons>
  <opinion>Boas imagens e muitos recursos. Bom custo benefício. Compraria de novo.

O que gostei: Boas imagens e muitos recursos. Bom custo benefício. Compraria de novo.

O que não gostei: Duração da bateria. Depois que passa para 2 tracinhos, voa para o zero...</opinion>
</review>
