<?xml version="1.0" ?>
<review>
  <source value="http://www.buscape.com.br/avaliacao--recomendo--fujifilm-finepix-s5100-4-0-megapixels--4689.html"/>
  <evaluation_date value="26/12/2005"/>
  <category value="Câmera Digital"/>
  <product value="Câmera Digital Fujifilm FinePix S5100 4.0 Megapixels"/>
  <stars value="4.0"/>
  <recommends value="Yes"/>
  <user value="6082"/>
  <thumbsUp value="0"/>
  <thumbsDown value="0"/>
  <pros>Duração da Bateria
Custo-Benefício
Qualidade da Imagem
Facilidade de Uso
Portabilidade
Funções e Características
</pros>
  <cons>Memória Inclusa
Display
</cons>
  <opinion>Li bastante os reviews pela internet antes compra-lo.

Estou muito satisfeito com o produto. Recomendo à todos.

Para terem uma idéia da qualidade das imagens, visitem:

www.flickr.com/photos/dneto

O que gostei: Excelente Pegada
Total controle sobre abertura, velocidade de shutter, compensação, etc.
Zoom Sensacional de 10x


O que não gostei: Falta de Dispositivo IS (Image Stabilization) porém nada que um tripé ou costume com a máquina não resolva.</opinion>
</review>
