<?xml version="1.0" ?>
<review>
  <source value="http://www.buscape.com.br/avaliacao--elogios--mitsuca-dc7328br-7-0-megapixels--57418.html"/>
  <evaluation_date value="18/10/2009"/>
  <category value="Câmera Digital"/>
  <product value="Câmera Digital Mitsuca DC7328BR 7.0 Megapixels"/>
  <stars value="4.0"/>
  <recommends value="Yes"/>
  <user value="19323"/>
  <thumbsUp value="0"/>
  <thumbsDown value="0"/>
  <pros>Duração da Bateria
Custo-Benefício
Qualidade da Imagem
Facilidade de Uso
Portabilidade
Funções e Características
Display
</pros>
  <cons>Memória Inclusa
</cons>
  <opinion>Zoom muito bom. cartão de memoria de baixo custo. Grava çaõ ótima. bons reursos.

O que gostei: Tudo de bom! Maquina rapida, grava com perfeição audio</opinion>
</review>
