<?xml version="1.0" ?>
<review>
  <source value="http://www.buscape.com.br/avaliacao--e-tudo-de-bom--sony-cyber-shot-dsc-h9-8-1-megapixels--60971.html"/>
  <evaluation_date value="18/11/2009"/>
  <category value="Câmera Digital"/>
  <product value="Câmera Digital Sony Cyber-shot DSC-H9 8.1 Megapixels"/>
  <stars value="4.0"/>
  <recommends value="Yes"/>
  <user value="7825"/>
  <thumbsUp value="0"/>
  <thumbsDown value="0"/>
  <pros>Duração da Bateria
Custo-Benefício
Qualidade da Imagem
Facilidade de Uso
Portabilidade
Funções e Características
Memória Inclusa
Display
</pros>
  <cons>Não possui nenhum ponto negativo.
</cons>
  <opinion>Eu a comprei em Paris, o preço foi de menos de 200 euros, descontado os impostos. Excelente compra.

O que gostei: Ela simplismente é tudo o q eu poderia esperar de uma máquina digital, bom preço, ótima qualidade e fácil de usar.

O que não gostei: É um pouco grande, e um pouco difícil seu acessórios</opinion>
</review>
