<?xml version="1.0" ?>
<review>
  <source value="http://www.buscape.com.br/avaliacao--vale-o-custo-beneficio--fujifilm-a220-12-2-megapixels--103202.html"/>
  <evaluation_date value="28/06/2010"/>
  <category value="Câmera Digital"/>
  <product value="Câmera Digital Fujifilm A220 12.2 Megapixels"/>
  <stars value="4.0"/>
  <recommends value="Yes"/>
  <user value="7303"/>
  <thumbsUp value="1"/>
  <thumbsDown value="0"/>
  <pros>Duração da Bateria
Custo-Benefício
Qualidade da Imagem
Facilidade de Uso
Portabilidade
Funções e Características
Memória Inclusa
Display
</pros>
  <cons>Não possui nenhum ponto negativo.
</cons>
  <opinion>Estou bastante satisfeita com a máquina. Atendeu as minhas expectativas, só estou tendo um pouco de dificuldade com o face detection, pois a máquina não detecta os rostos com facilidade.

O que gostei: Imagem ótima, facilidade na programação

O que não gostei: Dificuldade para usar o face detection</opinion>
</review>
