<?xml version="1.0" ?>
<review>
  <source value="http://www.buscape.com.br/avaliacao--camera-digital-mirage--mirage-trend-dc100-14-0-megapixels--205870.html"/>
  <evaluation_date value="03/06/2011"/>
  <category value="Câmera Digital"/>
  <product value="Câmera Digital Mirage Trend DC100 14.0 Megapixels"/>
  <stars value="4.0"/>
  <recommends value="Yes"/>
  <user value="7303"/>
  <thumbsUp value="3"/>
  <thumbsDown value="1"/>
  <pros>Duração da Bateria
Custo-Benefício
Qualidade da Imagem
Facilidade de Uso
Portabilidade
Memória Inclusa
Display
</pros>
  <cons>Funções e Características
</cons>
  <opinion>muito leve facil de carregar e de manusear

O que gostei: bateria de boa duraçao

O que não gostei: o flasch é muito forte e deixa as fotos tiradas de perto muito clara</opinion>
</review>
