<?xml version="1.0" ?>
<review>
  <source value="http://www.buscape.com.br/avaliacao--otima--sony-cyber-shot-dsc-w125-7-2-megapixels--34749.html"/>
  <evaluation_date value="24/01/2009"/>
  <category value="Câmera Digital"/>
  <product value="Câmera Digital Sony Cyber-shot DSC-W125 7.2 Megapixels"/>
  <stars value="4.0"/>
  <recommends value=""/>
  <user value="3300"/>
  <thumbsUp value="4"/>
  <thumbsDown value="2"/>
  <pros>Duração da Bateria
Custo-Benefício
Qualidade da Imagem
Facilidade de Uso
Portabilidade
Funções e Características
Memória Inclusa
Display
</pros>
  <cons>Não possui nenhum ponto negativo.
</cons>
  <opinion>comprei ela no Natal é uma exelente camera, tanto que 10 dias depois recebi um e-mail de uma loja me oferecendo uma dsc-w130 pelo mesmo preço comprei, tanto que no dia 23 de janeiro recebi um e-mail da Sony style, me oferecendo uma dsc-w200 pelo preço de uma dsc-w130 não pensei 2 vezes,hoje acabei de receber  camera é maravilhosa deixa a 125, e a 130, no chinelo, Sony é Sony e ponto.






O que gostei: Sony, é isso só, Sony!!!!

O que não gostei: rsrsrsrsrsrsrsrsr</opinion>
</review>
