<?xml version="1.0" ?>
<review>
  <source value="http://www.buscape.com.br/avaliacao--otimo-vendedor--oregon-scientific-ds9320-5-0-megapixels--15972.html"/>
  <evaluation_date value="09/05/2007"/>
  <category value="Câmera Digital"/>
  <product value="Câmera Digital Oregon Scientific DS9320 5.0 Megapixels"/>
  <stars value="4.0"/>
  <recommends value="Yes"/>
  <user value="26225"/>
  <thumbsUp value="6"/>
  <thumbsDown value="2"/>
  <pros>Custo-Benefício
Qualidade da Imagem
Facilidade de Uso
Portabilidade
Funções e Características
Display
</pros>
  <cons>Duração da Bateria
Memória Inclusa
</cons>
  <opinion>O produto é muito bom, preço legal e facil de usar, recomendo super simples o manuseio tb.

O que gostei: Além de achar o preço bom, a entrega foi super rapida, gostei do atendimento. Foram rapidos nas perguntas. Eu recomendo e aprovo.

O que não gostei: Nada a declarar</opinion>
</review>
