<?xml version="1.0" ?>
<review>
  <source value="http://www.buscape.com.br/avaliacao--nikon-l810--nikon-coolpix-l810-16-1-megapixels--392383.html"/>
  <evaluation_date value="14/12/2012"/>
  <category value="Câmera Digital"/>
  <product value="Câmera Digital Nikon Coolpix L810 16.1 Megapixels"/>
  <stars value="4.0"/>
  <recommends value="Yes"/>
  <user value="7303"/>
  <thumbsUp value="0"/>
  <thumbsDown value="1"/>
  <pros>Duração da Bateria
Custo-Benefício
Qualidade da Imagem
Portabilidade
Funções e Características
Memória Inclusa
Display
</pros>
  <cons>Facilidade de Uso
</cons>
  <opinion>Otimo produto, tem todas as funções que uma maquina pode ter, mais para mexer é preciso ter aula de fotografia (dependendo do lugar que quer fotografar), mais mesmo assim estou muito satisfeita!

O que gostei: excelente maquina, tem tudo!

O que não gostei: muito dificil de mexer!</opinion>
</review>
